simplexai/__init__.py
simplexai/version.py
simplexai/experiments/__init__.py
simplexai/experiments/breast_cancer.py
simplexai/experiments/mnist.py
simplexai/experiments/prostate_cancer.py
simplexai/experiments/time_series.py
simplexai/experiments/time_series_prostate_cancer.py
simplexai/experiments/use_case.py
simplexai/experiments/results/ar/outlier/plot_results.py
simplexai/experiments/results/ar/quality/plot_results.py
simplexai/experiments/results/mnist/influence/plot_results.py
simplexai/experiments/results/mnist/outlier/plot_results.py
simplexai/experiments/results/mnist/quality/plot_results.py
simplexai/experiments/results/prostate/outlier/plot_results.py
simplexai/experiments/results/prostate/quality/plot_results.py
simplexai/explainers/__init__.py
simplexai/explainers/nearest_neighbours.py
simplexai/explainers/representer.py
simplexai/explainers/simplex.py
simplexai/models/__init__.py
simplexai/models/base.py
simplexai/models/image_recognition.py
simplexai/models/linear_regression.py
simplexai/models/recurrent_neural_net.py
simplexai/models/tabular_data.py
simplexai/models/time_series_forecasting.py
simplexai/models/two_linear_layers.py
simplexai/utils/__init__.py
simplexai/utils/schedulers.py
simplexai/visualization/__init__.py
simplexai/visualization/images.py
simplexai/visualization/tables.py
simplexai/visualization/time_series.py
simplexai-0.0.3.dist-info/LICENSE
simplexai-0.0.3.dist-info/METADATA
simplexai-0.0.3.dist-info/WHEEL
simplexai-0.0.3.dist-info/top_level.txt
simplexai-0.0.3.dist-info/RECORD
