Metadata-Version: 2.1
Name: simplexai
Version: 0.0.3
Summary: SimplEx - Explaining Latent Representations with a Corpus of Examples
Home-page: https://www.vanderschaar-lab.com/
Author: Jonathan Crabbé
Author-email: jc2133@cam.ac.uk
License: MIT
Project-URL: Documentation, https://pyscaffold.org/
Platform: any
Classifier: Programming Language :: Python :: 3
Classifier: Topic :: Scientific/Engineering :: Artificial Intelligence
Classifier: Intended Audience :: Science/Research
Classifier: License :: OSI Approved :: MIT License
Classifier: Operating System :: OS Independent
Requires-Dist: captum (>=0.4.0)
Requires-Dist: numpy (>=1.21.6)
Requires-Dist: matplotlib
Requires-Dist: pandas (>=1.3.3)
Requires-Dist: pytorch-influence-functions (==0.1.1)
Requires-Dist: scikit-learn (>=1.0.2)
Requires-Dist: seaborn (>=0.11.2)
Requires-Dist: torch (>=1.9.1)
Requires-Dist: torchvision (>=0.10.1)
Requires-Dist: importlib-metadata ; python_version < "3.8"
Provides-Extra: testing
Requires-Dist: pre-commit ; extra == 'testing'
Requires-Dist: pytest ; extra == 'testing'
Requires-Dist: pytest-cov ; extra == 'testing'
Requires-Dist: bandit ; extra == 'testing'
Requires-Dist: jupyter ; extra == 'testing'
Requires-Dist: notebook ; extra == 'testing'
